{
  "@context": {
    "@version": 1.1,
    "@vocab": "http://tun.fi/",
    "@base": "http://tun.fi/",
    "default": "http://tun.fi/",
    "luomus": "http://id.luomus.fi/",
    "zmuo": "http://id.zmuo.oulu.fi/",
    "herbo": "http://id.herb.oulu.fi/",
    "utu": "http://mus.utu.fi/",
    "xsd": "https://www.w3.org/TR/xmlschema-2/#",
    "rdf": "http://www.w3.org/1999/02/22-rdf-syntax-ns#",
    "rdfs": "http://www.w3.org/2000/01/rdf-schema#",
    "xml": "http://www.w3.org/XML/1998/namespace#",
    "owl": "http://www.w3.org/2002/07/owl#",
    "dwc": "http://rs.tdwg.org/dwc/terms/",
    "dc": "http://purl.org/dc/terms/",
    "dwctype": "http://rs.tdwg.org/dwc/dwctype/",
    "abcd": "http://www.tdwg.org/schemas/abcd/2.06#",
    "naturforskaren": "http://naturforskaren.se/",
    "eol": "http://eol.org/",
    "skos": "http://www.w3.org/2004/02/skos/core#",
    "dyntaxa": "http://dyntaxa.se/Taxon/Info/",
    "taxonid": "http://taxonid.org/",
    "@context": {
      "@id": "default:@context",
      "@type": "xsd:string"
    },
    "id": "@id",
    "@type": {
      "@id": "default:@type",
      "@type": "xsd:string"
    },
    "batCollector": {
      "@id": "default:MY.batCollector",
      "@type": "@id"
    },
    "binocularsUsed": {
      "@id": "default:MY.binocularsUsed",
      "@type": "xsd:boolean"
    },
    "censusAreaHectares": {
      "@id": "default:MY.censusAreaHectares",
      "@type": "xsd:nonNegativeInteger"
    },
    "invasiveControlOtherExpensesInEuros": {
      "@id": "default:MY.invasiveControlOtherExpensesInEuros",
      "@type": "xsd:nonNegativeInteger"
    },
    "invasiveControlWorkHours": {
      "@id": "default:MY.invasiveControlWorkHours",
      "@type": "xsd:nonNegativeInteger"
    },
    "lineTransectSegmentCounted": {
      "@id": "default:MY.lineTransectSegmentCounted",
      "@type": "xsd:boolean"
    },
    "lineTransectSegmentMetersEnd": {
      "@id": "default:MY.lineTransectSegmentMetersEnd",
      "@type": "xsd:nonNegativeInteger"
    },
    "lineTransectSegmentMetersStart": {
      "@id": "default:MY.lineTransectSegmentMetersStart",
      "@type": "xsd:nonNegativeInteger"
    },
    "observedAreaHectares": {
      "@id": "default:MY.observedAreaHectares",
      "@type": "xsd:nonNegativeInteger"
    },
    "pointCountHabitat": {
      "@id": "default:MY.pointCountHabitat",
      "@type": "@id"
    },
    "shorelineLengthMeters": {
      "@id": "default:MY.shorelineLengthMeters",
      "@type": "xsd:nonNegativeInteger"
    },
    "spottingScopeUsed": {
      "@id": "default:MY.spottingScopeUsed",
      "@type": "xsd:boolean"
    },
    "sunniness": {
      "@id": "default:MY.sunniness",
      "@type": "xsd:nonNegativeInteger"
    },
    "sykeButterFlyCensusWind": {
      "@id": "default:MY.sykeButterFlyCensusWind",
      "@type": "@id"
    },
    "sykeButterFlyCensusWindEnd": {
      "@id": "default:MY.sykeButterFlyCensusWindEnd",
      "@type": "@id"
    },
    "sykeButterFlyCensusWindStart": {
      "@id": "default:MY.sykeButterFlyCensusWindStart",
      "@type": "@id"
    },
    "waterbirdCensusPeriod": {
      "@id": "default:MY.waterbirdCensusPeriod",
      "@type": "@id"
    },
    "waterbirdHabitat": {
      "@id": "default:MY.waterbirdHabitat",
      "@type": "@id"
    },
    "ACAFLAonAlder": {
      "@id": "default:WBC.ACAFLAonAlder",
      "@type": "xsd:nonNegativeInteger"
    },
    "ACAFLAonBirch": {
      "@id": "default:WBC.ACAFLAonBirch",
      "@type": "xsd:nonNegativeInteger"
    },
    "ACAFLAonGround": {
      "@id": "default:WBC.ACAFLAonGround",
      "@type": "xsd:nonNegativeInteger"
    },
    "ACAFLAonPine": {
      "@id": "default:WBC.ACAFLAonPine",
      "@type": "xsd:nonNegativeInteger"
    },
    "ACAFLAonSpruce": {
      "@id": "default:WBC.ACAFLAonSpruce",
      "@type": "xsd:nonNegativeInteger"
    },
    "CARSPIonAlder": {
      "@id": "default:WBC.CARSPIonAlder",
      "@type": "xsd:nonNegativeInteger"
    },
    "CARSPIonBirch": {
      "@id": "default:WBC.CARSPIonBirch",
      "@type": "xsd:nonNegativeInteger"
    },
    "CARSPIonGround": {
      "@id": "default:WBC.CARSPIonGround",
      "@type": "xsd:nonNegativeInteger"
    },
    "CARSPIonPine": {
      "@id": "default:WBC.CARSPIonPine",
      "@type": "xsd:nonNegativeInteger"
    },
    "CARSPIonSpruce": {
      "@id": "default:WBC.CARSPIonSpruce",
      "@type": "xsd:nonNegativeInteger"
    },
    "LOXIAonAlder": {
      "@id": "default:WBC.LOXIAonAlder",
      "@type": "xsd:nonNegativeInteger"
    },
    "LOXIAonBirch": {
      "@id": "default:WBC.LOXIAonBirch",
      "@type": "xsd:nonNegativeInteger"
    },
    "LOXIAonGround": {
      "@id": "default:WBC.LOXIAonGround",
      "@type": "xsd:nonNegativeInteger"
    },
    "LOXIAonPine": {
      "@id": "default:WBC.LOXIAonPine",
      "@type": "xsd:nonNegativeInteger"
    },
    "LOXIAonSpruce": {
      "@id": "default:WBC.LOXIAonSpruce",
      "@type": "xsd:nonNegativeInteger"
    },
    "abundanceBOMGAR": {
      "@id": "default:WBC.abundanceBOMGAR",
      "@type": "@id"
    },
    "abundancePINENU": {
      "@id": "default:WBC.abundancePINENU",
      "@type": "@id"
    },
    "abundanceTURPIL": {
      "@id": "default:WBC.abundanceTURPIL",
      "@type": "@id"
    },
    "birdFeederCount": {
      "@id": "default:WBC.birdFeederCount",
      "@type": "xsd:nonNegativeInteger"
    },
    "birdFeederCountBiotopeA": {
      "@id": "default:WBC.birdFeederCountBiotopeA",
      "@type": "xsd:nonNegativeInteger"
    },
    "birdFeederCountBiotopeB": {
      "@id": "default:WBC.birdFeederCountBiotopeB",
      "@type": "xsd:nonNegativeInteger"
    },
    "birdFeederCountBiotopeC": {
      "@id": "default:WBC.birdFeederCountBiotopeC",
      "@type": "xsd:nonNegativeInteger"
    },
    "birdFeederCountBiotopeD": {
      "@id": "default:WBC.birdFeederCountBiotopeD",
      "@type": "xsd:nonNegativeInteger"
    },
    "birdFeederCountBiotopeE": {
      "@id": "default:WBC.birdFeederCountBiotopeE",
      "@type": "xsd:nonNegativeInteger"
    },
    "birdFeederCountBiotopeF": {
      "@id": "default:WBC.birdFeederCountBiotopeF",
      "@type": "xsd:nonNegativeInteger"
    },
    "birdFeederCountBiotopeG": {
      "@id": "default:WBC.birdFeederCountBiotopeG",
      "@type": "xsd:nonNegativeInteger"
    },
    "birdFeederCountBiotopeH": {
      "@id": "default:WBC.birdFeederCountBiotopeH",
      "@type": "xsd:nonNegativeInteger"
    },
    "cloudAndRain": {
      "@id": "default:WBC.cloudAndRain",
      "@type": "@id"
    },
    "descriptionBiotopeF": {
      "@id": "default:WBC.descriptionBiotopeF",
      "@type": "xsd:string"
    },
    "feedingStationCount": {
      "@id": "default:WBC.feedingStationCount",
      "@type": "xsd:nonNegativeInteger"
    },
    "feedingStationCountBiotopeA": {
      "@id": "default:WBC.feedingStationCountBiotopeA",
      "@type": "xsd:nonNegativeInteger"
    },
    "feedingStationCountBiotopeB": {
      "@id": "default:WBC.feedingStationCountBiotopeB",
      "@type": "xsd:nonNegativeInteger"
    },
    "feedingStationCountBiotopeC": {
      "@id": "default:WBC.feedingStationCountBiotopeC",
      "@type": "xsd:nonNegativeInteger"
    },
    "feedingStationCountBiotopeD": {
      "@id": "default:WBC.feedingStationCountBiotopeD",
      "@type": "xsd:nonNegativeInteger"
    },
    "feedingStationCountBiotopeE": {
      "@id": "default:WBC.feedingStationCountBiotopeE",
      "@type": "xsd:nonNegativeInteger"
    },
    "feedingStationCountBiotopeF": {
      "@id": "default:WBC.feedingStationCountBiotopeF",
      "@type": "xsd:nonNegativeInteger"
    },
    "feedingStationCountBiotopeG": {
      "@id": "default:WBC.feedingStationCountBiotopeG",
      "@type": "xsd:nonNegativeInteger"
    },
    "feedingStationCountBiotopeH": {
      "@id": "default:WBC.feedingStationCountBiotopeH",
      "@type": "xsd:nonNegativeInteger"
    },
    "iceCover": {
      "@id": "default:WBC.iceCover",
      "@type": "@id"
    },
    "meanTemperature": {
      "@id": "default:WBC.meanTemperature",
      "@type": "xsd:integer"
    },
    "observerCount": {
      "@id": "default:WBC.observerCount",
      "@type": "xsd:positiveInteger"
    },
    "observerID": {
      "@id": "default:WBC.observerID",
      "@type": "xsd:nonNegativeInteger"
    },
    "pineConesAtCensus": {
      "@id": "default:WBC.pineConesAtCensus",
      "@type": "@id"
    },
    "routeID": {
      "@id": "default:WBC.routeID",
      "@type": "xsd:nonNegativeInteger"
    },
    "routeLength": {
      "@id": "default:WBC.routeLength",
      "@type": "xsd:nonNegativeInteger"
    },
    "routeLengthBiotopeA": {
      "@id": "default:WBC.routeLengthBiotopeA",
      "@type": "xsd:nonNegativeInteger"
    },
    "routeLengthBiotopeB": {
      "@id": "default:WBC.routeLengthBiotopeB",
      "@type": "xsd:nonNegativeInteger"
    },
    "routeLengthBiotopeC": {
      "@id": "default:WBC.routeLengthBiotopeC",
      "@type": "xsd:nonNegativeInteger"
    },
    "routeLengthBiotopeD": {
      "@id": "default:WBC.routeLengthBiotopeD",
      "@type": "xsd:nonNegativeInteger"
    },
    "routeLengthBiotopeE": {
      "@id": "default:WBC.routeLengthBiotopeE",
      "@type": "xsd:nonNegativeInteger"
    },
    "routeLengthBiotopeF": {
      "@id": "default:WBC.routeLengthBiotopeF",
      "@type": "xsd:nonNegativeInteger"
    },
    "routeLengthBiotopeG": {
      "@id": "default:WBC.routeLengthBiotopeG",
      "@type": "xsd:nonNegativeInteger"
    },
    "routeLengthBiotopeH": {
      "@id": "default:WBC.routeLengthBiotopeH",
      "@type": "xsd:nonNegativeInteger"
    },
    "routeLengthChange": {
      "@id": "default:WBC.routeLengthChange",
      "@type": "xsd:integer"
    },
    "routeLengthChangeBiotopeA": {
      "@id": "default:WBC.routeLengthChangeBiotopeA",
      "@type": "xsd:integer"
    },
    "routeLengthChangeBiotopeB": {
      "@id": "default:WBC.routeLengthChangeBiotopeB",
      "@type": "xsd:integer"
    },
    "routeLengthChangeBiotopeC": {
      "@id": "default:WBC.routeLengthChangeBiotopeC",
      "@type": "xsd:integer"
    },
    "routeLengthChangeBiotopeD": {
      "@id": "default:WBC.routeLengthChangeBiotopeD",
      "@type": "xsd:integer"
    },
    "routeLengthChangeBiotopeE": {
      "@id": "default:WBC.routeLengthChangeBiotopeE",
      "@type": "xsd:integer"
    },
    "routeLengthChangeBiotopeF": {
      "@id": "default:WBC.routeLengthChangeBiotopeF",
      "@type": "xsd:integer"
    },
    "routeLengthChangeBiotopeG": {
      "@id": "default:WBC.routeLengthChangeBiotopeG",
      "@type": "xsd:integer"
    },
    "routeLengthChangeBiotopeH": {
      "@id": "default:WBC.routeLengthChangeBiotopeH",
      "@type": "xsd:integer"
    },
    "snowAndIceOnTrees": {
      "@id": "default:WBC.snowAndIceOnTrees",
      "@type": "@id"
    },
    "snowCover": {
      "@id": "default:WBC.snowCover",
      "@type": "@id"
    },
    "sorbusBerriesAtCensus": {
      "@id": "default:WBC.sorbusBerriesAtCensus",
      "@type": "@id"
    },
    "sorbusBerriesEarlyFall": {
      "@id": "default:WBC.sorbusBerriesEarlyFall",
      "@type": "@id"
    },
    "spruceConesAtCensus": {
      "@id": "default:WBC.spruceConesAtCensus",
      "@type": "@id"
    },
    "typeOfSnowCover": {
      "@id": "default:WBC.typeOfSnowCover",
      "@type": "@id"
    },
    "visibility": {
      "@id": "default:WBC.visibility",
      "@type": "@id"
    },
    "waterbodies": {
      "@id": "default:WBC.waterbodies",
      "@type": "@id"
    },
    "wayOfTravel": {
      "@id": "default:WBC.wayOfTravel",
      "@type": "@id"
    },
    "wayOfTravelNotes": {
      "@id": "default:WBC.wayOfTravelNotes",
      "@type": "xsd:string"
    },
    "wind": {
      "@id": "default:WBC.wind",
      "@type": "@id"
    }
  }
}