{
  "$schema": "http://json-schema.org/schema#",
  "type": "object",
  "subject": "MKV.habitatObject",
  "additionalProperties": false,
  "title": "IUCN Red List Evaluation Habitat",
  "description": "",
  "properties": {
    "@context": {
      "type": "string",
      "range": "xsd:string",
      "subject": "@context",
      "title": "Context for the IUCN Red List Evaluation Habitat"
    },
    "id": {
      "type": "string",
      "range": "xsd:string",
      "subject": "id",
      "title": "Id for the IUCN Red List Evaluation Habitat"
    },
    "@type": {
      "type": "string",
      "range": "xsd:string",
      "subject": "@type",
      "title": "Type for the IUCN Red List Evaluation Habitat"
    },
    "herbo:sortOrder": {
      "type": "integer",
      "range": "xsd:integer",
      "subject": "herbo:sortOrder",
      "title": "herbo:sortOrder"
    },
    "habitat": {
      "type": "string",
      "enum": [
        "MKV.habitatM",
        "MKV.habitatMk",
        "MKV.habitatMkk",
        "MKV.habitatMkt",
        "MKV.habitatMl",
        "MKV.habitatMlt",
        "MKV.habitatMlk",
        "MKV.habitatMt",
        "MKV.habitatMtl",
        "MKV.habitatS",
        "MKV.habitatSl",
        "MKV.habitatSla",
        "MKV.habitatSlr",
        "MKV.habitatSlk",
        "MKV.habitatSn",
        "MKV.habitatSnk",
        "MKV.habitatSnr",
        "MKV.habitatSr",
        "MKV.habitatSrk",
        "MKV.habitatSrr",
        "MKV.habitatSk",
        "MKV.habitatSkk",
        "MKV.habitatSkr",
        "MKV.habitatV",
        "MKV.habitatVi",
        "MKV.habitatVik",
        "MKV.habitatVim",
        "MKV.habitatVis",
        "MKV.habitatVih",
        "MKV.habitatVie",
        "MKV.habitatVip",
        "MKV.habitatVs",
        "MKV.habitatVsk",
        "MKV.habitatVsr",
        "MKV.habitatVa",
        "MKV.habitatVj",
        "MKV.habitatVp",
        "MKV.habitatVk",
        "MKV.habitatVl",
        "MKV.habitatR",
        "MKV.habitatRi",
        "MKV.habitatRim",
        "MKV.habitatRimt",
        "MKV.habitatRiml",
        "MKV.habitatRip",
        "MKV.habitatRin",
        "MKV.habitatRil",
        "MKV.habitatRir",
        "MKV.habitatRis",
        "MKV.habitatRih",
        "MKV.habitatRit",
        "MKV.habitatRj",
        "MKV.habitatRjm",
        "MKV.habitatRjmt",
        "MKV.habitatRjml",
        "MKV.habitatRjp",
        "MKV.habitatRjn",
        "MKV.habitatRjl",
        "MKV.habitatRjr",
        "MKV.habitatRjs",
        "MKV.habitatRjh",
        "MKV.habitatRjt",
        "MKV.habitatK",
        "MKV.habitatKk",
        "MKV.habitatKs",
        "MKV.habitatKr",
        "MKV.habitatKl",
        "MKV.habitatKm",
        "MKV.habitatT",
        "MKV.habitatTk",
        "MKV.habitatTn",
        "MKV.habitatTu",
        "MKV.habitatTp",
        "MKV.habitatTl",
        "MKV.habitatTll",
        "MKV.habitatTlk",
        "MKV.habitatTls",
        "MKV.habitatTlr",
        "MKV.habitatTlä",
        "MKV.habitatTs",
        "MKV.habitatTj",
        "MKV.habitatTv",
        "MKV.habitatTa",
        "MKV.habitatI",
        "MKV.habitatIn",
        "MKV.habitatIt",
        "MKV.habitatIh",
        "MKV.habitatIk",
        "MKV.habitatIo",
        "MKV.habitatIv",
        "MKV.habitatIp",
        "MKV.habitatIu",
        "MKV.habitatIr",
        "MKV.habitatU"
      ],
      "enumNames": [
        "M – Forests",
        "Mk – heath forests",
        "Mkk – sub-xeric, xeric and barren heath forests",
        "Mkt – mesic and herb-rich heath forests",
        "Ml – herb-rich forests (also spruce-dominated)",
        "Mlt – dry and mesic herb-rich forests",
        "Mlk – moist herb-rich forests",
        "Mt – alpine birch forests (excluding herb-rich alpine birch forests)",
        "Mtl – herb-rich alpine birch forests",
        "S – Mires",
        "Sl – rich fens",
        "Sla – open rich fens",
        "Slr – rich pine fens",
        "Slk – rich spruce-birch fens",
        "Sn – fens",
        "Snk – ombro- and oligotrophic fens",
        "Snr – mesotrophic fens",
        "Sr – pine mires",
        "Srk – ombro- and oligotrophic pine mires",
        "Srr – mesotrophic pine mires",
        "Sk – spruce mires",
        "Skk – oligotrophic spruce mires",
        "Skr – eutrophic and mesotrophic spruce mires",
        "V – Aquatic habitats",
        "Vi – Baltic Sea",
        "Vik – benthic habitats characterized by rocks and boulders",
        "Vim – benthic habitats characterized by mud and silt",
        "Vis – benthic habitats characterized by gravel",
        "Vih – benthic habitats characterized by sand",
        "Vie – mixed benthic habitats",
        "Vip – pelagic habitats",
        "Vs – lakes and ponds",
        "Vsk – oligotrophic lakes and ponds",
        "Vsr – eutrophic and mesotrophic lakes and ponds",
        "Va – small ponds (also in mires etc.)",
        "Vj – rivers",
        "Vp – brooks and streams",
        "Vk – rapids",
        "Vl – spring complexes",
        "R – Shores",
        "Ri – coastal shores",
        "Rim – coastal forests",
        "Rimt – coastal flooded forests",
        "Riml – coastal wooded swamps",
        "Rip – coastal shore scrubs",
        "Rin – coastal meadows",
        "Ril – coastal swamp shores",
        "Rir – coastal reedbeds with Phragmites australis",
        "Ris – coastal gravel-, shingle- and boulder shores",
        "Rih – coastal sand shores",
        "Rit – coastal open alluvial shores",
        "Rj – lake shores and river banks",
        "Rjm – inland forests on lake shores and river banks",
        "Rjmt – inland flooded forests",
        "Rjml – inland wooded swamps",
        "Rjp – inland shore scrubs",
        "Rjn – meadows on lake shores and river banks",
        "Rjl – inland swamp shores",
        "Rjr – inland reedbeds with Phragmites australis",
        "Rjs – inland gravel-, shingle- and boulder shores",
        "Rjh – sandy lake shores and river banks",
        "Rjt – inland open alluvial shores",
        "K – Rock outcrops and boulder fields",
        "Kk – calcareous rock outcrops and quarries",
        "Ks – serpentine rock outcrops",
        "Kr – canyons and gorges",
        "Kl – caves and crevices",
        "Km – siliceous rock outcrops",
        "T – Alpine habitats",
        "Tk – alpine heaths",
        "Tn – alpine meadows",
        "Tu – snowbeds",
        "Tp – alpine heath scrubs",
        "Tl – alpine rock outcrops and boulder fields",
        "Tll – alpine siliceous rock outcrops and boulder fields",
        "Tlk – alpine calcareous rock outcrops and boulder fields",
        "Tls – alpine serpentine rock outcrops and boulder fields",
        "Tlr – alpine gorges and canyons",
        "Tlä – alpine spring complexes and seepage areas",
        "Ts – alpine mires",
        "Tj – alpine ponds and lakes (shores included)",
        "Tv - paljakan virtavedet (sis. rannat)",
        "Ta - paljakan lampareet ja allikot",
        "I – Rural biotopes and cultural habitats",
        "In – seminatural dry meadows",
        "It – seminatural mesic meadows",
        "Ih – wooded pastures, pollard meadows and grazed woodlands",
        "Ik – seminatural moist meadows (excluding shore meadows)",
        "Io – ditches etc.",
        "Iv – arable land",
        "Ip - puistot, pihamaat ja puutarhat",
        "Iu – open habitats formed and maintained by heavy human influence",
        "Ir – buildings and constructions",
        "? – Habitat unknown"
      ],
      "range": "MKV.habitatEnum",
      "subject": "MKV.habitat",
      "title": "Elinympäristö"
    },
    "habitatSpecificType": {
      "type": "array",
      "uniqueItems": false,
      "items": {
        "type": "string",
        "enum": [
          "",
          "MKV.habitatSpecificTypeV",
          "MKV.habitatSpecificTypeH",
          "MKV.habitatSpecificTypeP",
          "MKV.habitatSpecificTypeJ",
          "MKV.habitatSpecificTypePAK",
          "MKV.habitatSpecificTypeVAK",
          "MKV.habitatSpecificTypeRA",
          "MKV.habitatSpecificTypeKA",
          "MKV.habitatSpecificTypeKE",
          "MKV.habitatSpecificTypeCA"
        ],
        "enumNames": [
          "",
          "v – old-growth forests (including sporadic old trees and younger forests with decaying trees)",
          "h – esker forests, also semi-open forests",
          "p – burnt forest areas and other young stages of natural succession",
          "j – broadleaved deciduous trees present",
          "pa – sun-exposed",
          "va – shady",
          "ra – on the shore (aquatic habitat is essential for the distribution of the species)",
          "ka – acidic rocks and boulder fields",
          "ke – intermediate-basic rock outcrops and boulder fields",
          "ca – calcareous effect"
        ]
      },
      "minItems": 0,
      "range": "MKV.habitatSpecificTypeEnum",
      "subject": "MKV.habitatSpecificType",
      "title": "Tarkenne"
    },
    "sortOrder": {
      "type": "integer",
      "range": "xsd:integer",
      "subject": "sortOrder",
      "title": "sortOrder"
    }
  },
  "required": [
    "habitat"
  ]
}